.gitignore
LICENSE
Makefile
README.md
pyproject.toml
setup.cfg
.github/pull_request_template.md
.github/ISSUE_TEMPLATE/bug_report.md
.github/ISSUE_TEMPLATE/feature_request.md
.github/workflows/coverage.yml
.github/workflows/publish_release.yml
.github/workflows/style.yml
src/orquestra/vqa/py.typed
src/orquestra/vqa/algorithms/__init__.py
src/orquestra/vqa/algorithms/qaoa.py
src/orquestra/vqa/algorithms/qcbm.py
src/orquestra/vqa/algorithms/vqe.py
src/orquestra/vqa/ansatz/__init__.py
src/orquestra/vqa/ansatz/kbody.py
src/orquestra/vqa/ansatz/qaoa_farhi.py
src/orquestra/vqa/ansatz/qaoa_warm_start.py
src/orquestra/vqa/ansatz/quantum_compiling.py
src/orquestra/vqa/ansatz/singlet_uccsd.py
src/orquestra/vqa/ansatz/qcbm/_qcbm.py
src/orquestra/vqa/ansatz/qcbm/_qcbm_utils.py
src/orquestra/vqa/api/ansatz.py
src/orquestra/vqa/api/ansatz_test.py
src/orquestra/vqa/api/ansatz_utils.py
src/orquestra/vqa/cost_function/__init__.py
src/orquestra/vqa/cost_function/cost_function.py
src/orquestra/vqa/cost_function/qcbm_cost_function.py
src/orquestra/vqa/estimation/__init__.py
src/orquestra/vqa/estimation/context_selection.py
src/orquestra/vqa/estimation/cvar.py
src/orquestra/vqa/estimation/gibbs_objective.py
src/orquestra/vqa/grouping/__init__.py
src/orquestra/vqa/grouping/_grouping.py
src/orquestra/vqa/openfermion/__init__.py
src/orquestra/vqa/openfermion/_openfermion_adapter.py
src/orquestra/vqa/openfermion/_openfermion_io.py
src/orquestra/vqa/openfermion/_openfermion_utils.py
src/orquestra/vqa/openfermion/_utils.py
src/orquestra/vqa/opt/__init__.py
src/orquestra/vqa/opt/fourier_qaoa.py
src/orquestra/vqa/opt/layerwise_ansatz_optimizer.py
src/orquestra/vqa/opt/recursive_qaoa.py
src/orquestra/vqa/parameter_initialization/__init__.py
src/orquestra/vqa/parameter_initialization/_qaoa_interp.py
src/orquestra/vqa/shot_allocation/__init__.py
src/orquestra/vqa/shot_allocation/_shot_allocation.py
src/orquestra/vqa/testing/__init__.py
src/orquestra/vqa/testing/mock_objects.py
src/orquestra_vqa.egg-info/PKG-INFO
src/orquestra_vqa.egg-info/SOURCES.txt
src/orquestra_vqa.egg-info/dependency_links.txt
src/orquestra_vqa.egg-info/not-zip-safe
src/orquestra_vqa.egg-info/requires.txt
src/orquestra_vqa.egg-info/top_level.txt
