Metadata-Version: 2.1
Name: orquestra-vqa
Version: 0.9.0
Summary: "Orquestra's library with code related to variational quantum algorithms."
Home-page: https://github.com/zapatacomputing/orquestra-vqa
Author: Zapata Computing Inc.
Author-email: info@zapatacomputing.com,
License: Apache Software License 2.0
Classifier: Programming Language :: Python :: 3
Classifier: Operating System :: OS Independent
Classifier: License :: OSI Approved :: Apache Software License
Classifier: Topic :: Scientific/Engineering
Requires-Python: !=3.9.7,>=3.9
License-File: LICENSE
Requires-Dist: orquestra-quantum
Requires-Dist: orquestra-opt
Requires-Dist: orquestra-cirq
Requires-Dist: numpy>=1.20
Requires-Dist: overrides>=3.10
Provides-Extra: dev
Requires-Dist: orquestra-python-dev; extra == "dev"
Requires-Dist: types-setuptools; extra == "dev"
